{
   "produtoras":[
      {
         "id":1,
         "nome":"produtora1"
      },
      {
         "id":2,
         "nome":"Josias Filmes"
      }
   ],
   "categorias":[
      {
         "id":1,
         "nome":"Ação"
      },
      {
         "id":2,
         "nome":"Terror"
      }
   ],
   "tiposTicket":[
      {
         "id":1,
         "nome":"tipo1"
      },
      {
         "id":2,
         "nome":"tipo2"
      }
   ],
   "tiposExibicao":[
      {
         "id":1,
         "nome":"tipo1"
      },
      {
         "id":2,
         "nome":"tipo2"
      }
   ]
}
